magnato_calc/__init__.py
magnato_calc/calculator.py
magnato_calc-0.1.2.dist-info/METADATA
magnato_calc-0.1.2.dist-info/WHEEL
magnato_calc-0.1.2.dist-info/entry_points.txt
magnato_calc-0.1.2.dist-info/top_level.txt
magnato_calc-0.1.2.dist-info/RECORD
