Metadata-Version: 2.4
Name: magnato_calc
Version: 0.1.2
Summary: a simple calculator have multi options
Author: NeerajKr
Author-email: magnato1997@gmail.com
Classifier: Programming Language :: Python :: 3
Classifier: License :: OSI Approved :: MIT License
Classifier: Operating System :: OS Independent
Requires-Python: >=3.6
Dynamic: author
Dynamic: author-email
Dynamic: classifier
Dynamic: description
Dynamic: description-content-type
Dynamic: requires-python
Dynamic: summary
